lxdx/__init__.py
lxdx/dixt.py
lxdx-0.5.1.dist-info/LICENSE
lxdx-0.5.1.dist-info/METADATA
lxdx-0.5.1.dist-info/WHEEL
lxdx-0.5.1.dist-info/RECORD
