Metadata-Version: 2.3
Name: lxdx
Version: 0.5.1
Summary: Just an extended Python dict with attribute-accessibility, extra methods, and metadata
License: 3-Clause BSD License
Keywords: dict,extended,normalize,metadata
Author: Hardy Stones
Author-email: hardistones@hotmail.com
Requires-Python: >=3.9,<4.0
Classifier: Intended Audience :: Developers
Classifier: License :: OSI Approved :: BSD License
Classifier: License :: Other/Proprietary License
Classifier: Natural Language :: English
Classifier: Operating System :: OS Independent
Classifier: Programming Language :: Python :: 3
Classifier: Programming Language :: Python :: 3.9
Classifier: Programming Language :: Python :: 3.10
Classifier: Programming Language :: Python :: 3.11
Classifier: Programming Language :: Python :: 3.12
Classifier: Programming Language :: Python :: 3.13
Classifier: Topic :: Software Development
Classifier: Topic :: Software Development :: Libraries
Classifier: Topic :: Software Development :: Libraries :: Python Modules
Classifier: Topic :: Software Development :: Testing
Classifier: Topic :: Utilities
Project-URL: Bug Tracker, https://github.com/hardistones/lxdx/issues
Project-URL: Documentation, https://hardistones.github.io/lxdx
Project-URL: Homepage, https://github.com/hardistones/lxdx
